{
    "coc.preferences.extensionUpdateCheck": "daily",

    "suggest.acceptSuggestionOnCommitCharacter": true,
    "suggest.timeout": 5000,
    "suggest.noselect": true,
    "suggest.snippetIndicator": "  ❄",
    "suggest.completionItemKindLabels": {
        "class": "",
        "color": "",
        "constant": "",
        "default": "",
        "enum": "",
        "enumMember": "",
        "event": "鬒",
        "field": "m",
        "file": "",
        "folder": "",
        "function": "F",
        "interface": "",
        "keyword": "",
        "method": "f",
        "module": "",
        "operator": "Ψ",
        "property": "",
        "reference": "r",
        "snippet": "",
        "struct": "פּ",
        "text": "",
        "typeParameter": "",
        "unit": "",
        "value": "",
        "variable": ""
    },

    "prettier.tabWidth": 4,
    "prettier.eslintIntegration": true,

    "xml.java.home": "/usr/lib/jvm/default/",

    "yank.highlight.duration": 200,
    "yank.enableCompletion": false,

    "session.directory": "~/.cache/vim/sessions/",
    "session.saveOnVimLeave": true,

    "diagnostic.maxWindowHeight": 10,

    "list.maxPreviewHeight": 8,
    "list.source.grep.command": "rg",
    "list.source.grep.defaultArgs": [
        "--column",
        "--line-number",
        "--no-heading",
        "--color=always",
        "--smart-case"
    ],
    "list.source.lines.defaultArgs": ["-e"],
    "list.source.words.defaultArgs": ["-e"],
    "list.source.files.command": "rg",
    "list.source.files.args": ["--files"],
    "list.source.files.excludePatterns": [".git"],

    "explorer.icon.enableNerdfont": true,
    "explorer.bookmark.child.template": "[selection | 1] [filename] [position] - [annotation]",
    "explorer.previewAction.onHover": false,
    "explorer.keyMappings.global": {
        "k": "nodePrev",
        "j": "nodeNext",
        "h": "collapse",
        "l": ["expandable?", "expand", "open"],
        "L": "expand:recursive",
        "H": "collapse:recursive",
        "K": "expandablePrev",
        "J": "expandableNext",
        "<cr>": ["expandable?", "cd", "open"],
        "<bs>": "gotoParent",
        "r": "refresh",
        "v": ["toggleSelection", "normal:j"],
        "V": ["toggleSelection", "normal:k"],
        "*": "toggleSelection",
        "w": "open:split",
        "W": "open:vsplit",
        "t": "open:tab",
        "dd": "cutFile",
        "Y": "copyFile",
        "D": "delete",
        "P": "pasteFile",
        "R": "rename",
        "N": "addFile",
        "yp": "copyFilepath",
        "yn": "copyFilename",
        "gp": "preview:labeling",
        "x": "systemExecute",
        "f": "search",
        "F": "searchRecursive",
        "<tab>": "actionMenu",
        "?": "help",
        "q": "quit",
        "<esc>": "esc",
        "gf": "gotoSource:file",
        "gb": "gotoSource:buffer",
        "[[": "sourcePrev",
        "]]": "sourceNext",
        "[d": "diagnosticPrev",
        "]d": "diagnosticNext",
        "[c": "gitPrev",
        "]c": "gitNext",
        "<<": "gitStage",
        ">>": "gitUnstage"
    },

    "git.addGBlameToBufferVar": true,
    "git.addGBlameToVirtualText": true,
    "git.virtualTextPrefix": "  ➤  ",
    "git.addedSign.hlGroup": "GitGutterAdd",
    "git.changedSign.hlGroup": "GitGutterChange",
    "git.removedSign.hlGroup": "GitGutterDelete",
    "git.topRemovedSign.hlGroup": "GitGutterDelete",
    "git.changeRemovedSign.hlGroup": "GitGutterChangeDelete",
    "git.addedSign.text": "▎",
    "git.changedSign.text": "▎",
    "git.removedSign.text": "▎",
    "git.topRemovedSign.text": "▔",
    "git.changeRemovedSign.text": "▋",

    "snippets.ultisnips.enable": true,
    "snippets.ultisnips.directories": ["UltiSnips", "gosnippets/UltiSnips"],
    "snippets.extends": { "cpp": ["c", "cpp"], "typescript": ["javascript"] },

    "tsserver.log": "verbose",
    "tsserver.trace.server": "verbose",
    "tsserver.enable": true,

    "languageserver": {}
}
